riotwatcher/Deserializer.py
riotwatcher/LolWatcher.py
riotwatcher/LorWatcher.py
riotwatcher/RateLimiter.py
riotwatcher/TftWatcher.py
riotwatcher/ValWatcher.py
riotwatcher/__init__.py
riotwatcher/__version__.py
riotwatcher/exceptions.py
riotwatcher/riotwatcher.py
riotwatcher/Handlers/DeprecationHandler.py
riotwatcher/Handlers/DeserializerAdapter.py
riotwatcher/Handlers/DictionaryDeserializer.py
riotwatcher/Handlers/IllegalArgumentError.py
riotwatcher/Handlers/RateLimiterAdapter.py
riotwatcher/Handlers/RequestHandler.py
riotwatcher/Handlers/SanitationHandler.py
riotwatcher/Handlers/ThrowOnErrorHandler.py
riotwatcher/Handlers/TypeCorrectorHandler.py
riotwatcher/Handlers/__init__.py
riotwatcher/Handlers/RateLimit/ApplicationRateLimiter.py
riotwatcher/Handlers/RateLimit/BasicRateLimiter.py
riotwatcher/Handlers/RateLimit/HeaderBasedLimiter.py
riotwatcher/Handlers/RateLimit/InternalLimiter.py
riotwatcher/Handlers/RateLimit/Limits.py
riotwatcher/Handlers/RateLimit/MethodRateLimiter.py
riotwatcher/Handlers/RateLimit/OopsRateLimiter.py
riotwatcher/Handlers/RateLimit/__init__.py
riotwatcher/_apis/BaseApi.py
riotwatcher/_apis/Endpoint.py
riotwatcher/_apis/NamedEndpoint.py
riotwatcher/_apis/UrlConfig.py
riotwatcher/_apis/__init__.py
riotwatcher/_apis/helpers.py
riotwatcher/_apis/league_of_legends/ChallengesApiV1.py
riotwatcher/_apis/league_of_legends/ChampionApiV3.py
riotwatcher/_apis/league_of_legends/ChampionMasteryApiV4.py
riotwatcher/_apis/league_of_legends/ClashApiV1.py
riotwatcher/_apis/league_of_legends/DataDragonApi.py
riotwatcher/_apis/league_of_legends/LeagueApiV4.py
riotwatcher/_apis/league_of_legends/LolStatusApiV3.py
riotwatcher/_apis/league_of_legends/LolStatusApiV4.py
riotwatcher/_apis/league_of_legends/MatchApiV5.py
riotwatcher/_apis/league_of_legends/SpectatorApiV4.py
riotwatcher/_apis/league_of_legends/SummonerApiV4.py
riotwatcher/_apis/league_of_legends/__init__.py
riotwatcher/_apis/league_of_legends/urls/ChallengesApiV1Urls.py
riotwatcher-3.2.5.dist-info/LICENSE
riotwatcher-3.2.5.dist-info/METADATA
riotwatcher-3.2.5.dist-info/WHEEL
riotwatcher-3.2.5.dist-info/top_level.txt
riotwatcher-3.2.5.dist-info/RECORD
