Metadata-Version: 2.1
Name: riotwatcher
Version: 3.2.5
Summary: RiotWatcher is a thin wrapper on top of the Riot Games API for League of Legends.
Home-page: https://github.com/pseudonym117/Riot-Watcher
Author: AG Stephan
License: MIT
Classifier: License :: OSI Approved :: MIT License
Classifier: Topic :: Software Development :: Libraries :: Python Modules
Classifier: Topic :: Text Processing
Classifier: Topic :: Games/Entertainment :: Real Time Strategy
Classifier: Topic :: Games/Entertainment :: Role-Playing
Provides-Extra: dev
License-File: LICENSE
